soc4onnx/__init__.py
soc4onnx/__main__.py
soc4onnx/onnx_opset_change.py
soc4onnx-1.0.2.dist-info/LICENSE
soc4onnx-1.0.2.dist-info/METADATA
soc4onnx-1.0.2.dist-info/WHEEL
soc4onnx-1.0.2.dist-info/entry_points.txt
soc4onnx-1.0.2.dist-info/top_level.txt
soc4onnx-1.0.2.dist-info/RECORD
