Metadata-Version: 2.1
Name: soc4onnx
Version: 1.0.2
Summary: A very simple tool that forces a change in the opset of an ONNX graph.  Simple Opset Changer for ONNX.
Home-page: https://github.com/PINTO0309/soc4onnx
Author: Katsuya Hyodo
Author-email: rmsdh122@yahoo.co.jp
License: MIT License
Platform: linux
Platform: unix
Requires-Python: >=3.6
License-File: LICENSE
